shell_database/__init__.py
shell_database/__main__.py
shell_database/shdb.py
shell_database/store/__init__.py
shell_database/store/encryption.py
shell_database/store/store.py
shell_database-1.1.0.data/scripts/shdb
tests/__init__.py
tests/test_shell_database.py
shell_database-1.1.0.dist-info/LICENSE
shell_database-1.1.0.dist-info/METADATA
shell_database-1.1.0.dist-info/WHEEL
shell_database-1.1.0.dist-info/top_level.txt
shell_database-1.1.0.dist-info/RECORD
