Metadata-Version: 2.1
Name: shell-database
Version: 1.1.0
Summary: A key value store for the terminal
Home-page: https://github.com/jcoelho93/shell-database
Author: José Coelho
License: UNKNOWN
Platform: any
Classifier: Programming Language :: Python :: 3.8
Classifier: Topic :: Software Development :: Libraries :: Python Modules
Classifier: License :: OSI Approved :: MIT License
Requires-Python: >=3.8*
Requires-Dist: click (==7.1.2)
Requires-Dist: fuzzywuzzy (==0.18.0)
Requires-Dist: cryptography (==3.1)
Requires-Dist: python-Levenshtein (==0.12.2)
